autodiff/__init__.py
autodiff/dualnumber.py
autodiff/node.py
autodiff/operatorsfunc.py
autodiff_aabj-1.0.1.dist-info/LICENSE
autodiff_aabj-1.0.1.dist-info/METADATA
autodiff_aabj-1.0.1.dist-info/WHEEL
autodiff_aabj-1.0.1.dist-info/top_level.txt
autodiff_aabj-1.0.1.dist-info/RECORD
