Metadata-Version: 2.1
Name: autodiff-aabj
Version: 1.0.1
Summary: A simple autodiff library.
Home-page: https://github.com/cs107-sweet-16/cs107-FinalProject
Author: Albert Ge, Anna Wuest, Bhawesh Kumar, Jingxing Fang
Author-email: albertge@g.harvard.edu
License: UNKNOWN
Project-URL: Bug Tracker, https://github.com/cs107-sweet-16/cs107-FinalProject/issues
Platform: UNKNOWN
Classifier: Programming Language :: Python :: 3
Classifier: License :: OSI Approved :: MIT License
Classifier: Operating System :: OS Independent
Requires-Python: >=3.6
License-File: LICENSE
Requires-Dist: numpy (>=1.21.1)
